ESE 461/pipe report/mult.v
module mult( clk, reset, A, B, PRODUCT);

  input clk;
  input reset;

  input [15 : 0] A;
  input [15 : 0] B;
  output reg[15 : 0] PRODUCT;
  
  // Your code begins here
  reg [31:0] storeD, storeQ;
  reg [15:0] storeBD, storeBQ;
  reg [31:0] productD, productQ;
  reg [3:0] nextState, state;
  reg [6:0] counterD, counterQ;
  parameter init = 0,  step1 = 1,step2 = 2;
  //combination code and fsm
  //A muliplicand, and B is mulitplier
   always @ * begin
   storeD = storeQ;
   productD = productQ;
   storeBD = storeBQ;
   counterD = counterQ;
   nextState = state;
   
        case(state)
            init: begin
                storeD = 0;
                storeBD = B;
                productD = 0;
                counterD = 0;
                nextState = step1; 
            end
            
        step1: begin
           if(counterD < 32)begin
                if(B[counterQ]==1)begin
                    storeD = A << counterQ;
                    productD = productQ + storeQ;
                    counterD = counterQ + 1;
                end
                else begin
                    counterD = counterQ + 1;
                end
           end
           else begin
                productD = productQ + storeQ;
                nextState = step2;
           end
        end
        
        step2 : begin
              PRODUCT[7:0] = productQ[15:8];
              PRODUCT[15:8] = productQ[23:16];
              nextState = init;
        end
        endcase
   end
   
   //sequential logic
   always @ (posedge clk) begin
        if ( reset ) begin
            storeQ <= 0;
            counterQ <= 0;
            productQ <= 0;
            storeBQ <= 0;
            state <= init;
            
        end else begin
            counterQ <= counterD;
            storeQ <= storeD;
            storeBQ <= storeBD;
            productQ <= productD;
            state <= nextState;
        end
   end
endmodule

ESE 461/pipe report/ramB.v
`timescale 1ns / 1ps
//////////////////////////////////////////////////////////////////////////////////

//////////////////////////////////////////////////////////////////////////////////


               

module ramB_2 (clk, we, a, di, do);
    input clk;
    input we;
    input [5:0] a;
    input [15:0] di;
    output [15:0] do;
    reg [15:0] ram [9:0];
    integer i = 0;

    initial begin
    for(i=0; i<10 ; i=i+1)begin
       ram[i]<=16'b0;
    end
    end
    
    always @(posedge clk) begin    
        if (we) 
            ram[a] <= di;
        end


    assign do = ram[a];
    
endmodule

ESE 461/pipe report/ramA.v
`timescale 1ns / 1ps
//////////////////////////////////////////////////////////////////////////////////

//////////////////////////////////////////////////////////////////////////////////


               

module ramA_2 (clk, we, a, di, do);
    input clk;
    input we;
    input [5:0] a;
    input [15:0] di;
    output [15:0] do;
    reg [15:0] ram [9:0];
    integer i = 0;

    initial begin
    for(i=0; i<10 ; i=i+1)begin
       ram[i]<=16'b0;
    end
    end
    
    always @(posedge clk) begin    
        if (we)
            ram[a] <= di;
        end

    assign do = ram[a];
    
endmodule

Verilog Project/ESE 461/pipe report/pipe.v
`timescale 1ns / 1ps
//////////////////////////////////////////////////////////////////////////////////

// 
//////////////////////////////////////////////////////////////////////////////////


module pipe (clk, reset, A,B, result, wrAddr);
	
	input clk;
	input reset;
	input wire [3:0] wrAddr;
  
	input [15:0] A;
	input [15:0] B;
	output reg [15:0] result;
	
	wire [15:0] result2;
	
	reg weA;
    reg [8:0] aAD;
    reg [8:0] aAQ;
    wire signed [15:0] doA;
  
	ramA_2 ramA(
	.clk(clk),
	.we(weA),
	.a(aAQ),
	.di(A),
	.do(doA)
	);
	
 	reg weB;
    reg [8:0] aBD;
    reg [8:0] aBQ;
    wire signed [15:0] doB; 
    
    reg rd,md;

	ramB_2 ramB(
	.clk(clk),
	.we(weB),
	.a(aBQ),
	.di(B),
	.do(doB)
	);  
    reg [15:0] ramAD, ramAQ;
    reg [15:0] ramBD, ramBQ; 
    reg [15:0] multD, multQ;
    	
	mult mult(
	.clk(clk),
	.reset(reset),
	.A(ramAQ),
	.B(ramBQ),
	.PRODUCT(result2)
	);

	//Registers   
 
    reg [15:0] partialD, partialQ;
	reg [15:0] counterD, counterQ;
	reg [15:0] counter2D, counter2Q;
	reg [15:0] smult [9:0];

     
	//state machine
    
    reg [1:0] state, nextState;
    parameter Read=0, Mult=1,Fresult=2,store=3,wM=4;
    reg done;
    
    always @ * begin
		partialD = partialQ;
		ramAD = ramAQ;
		ramBD = ramBQ;
		multD = multQ;
		counter2D = 0;
		counterD = counterQ;
		weA=0;
		weB=0;
		done=1;	
		nextState=state;
		aAD = aAQ;
		aBD = aBQ;
		rd = 0;
		md = 0;
    
        case (state)   
            Read : begin
	              if(wrAddr == 2) begin
                    aAD = 0;
                    aBD = 0;
                    partialD = 0;
                    counterD = 0;
                    multD = 0;
                    nextState = Read;
                  end
                  if(wrAddr == 1) begin
                        weA = 1;    
                        weB = 1;
                        nextState = store;  
                  end
                  
            end
            
            store:begin
                weA = 1;
                weB = 1;
                ramAD = doA;
                if(aAQ < 11)begin
                    aAD =aAQ + 1;
                end else begin
                    aAD = 0;
                end 
                ramBD = doB;
                if(aBQ < 11)begin
                    aBD =aBQ + 1;
                end else begin
                    aBD = 0;
                end            
                nextState = Mult;      
            end
            
            
            Mult : begin               
                multD = result2; 
                if(counterD > 1) begin
                    partialD = partialQ + multQ;
                end
                counterD = counterQ + 1;
                nextState = Fresult;
			end
			
			Fresult: begin	    		   
				result = partialQ;				
			    nextState = Read;
			end

            default : begin
                nextState = Read;
            end
        endcase
    end
  
	
	//Sequential logic
	always @ (posedge clk) begin
        if (reset) begin
			partialQ <=0;
			counterQ <=0;
			counter2Q <=0;
			multQ<=0;
			aAQ <=0;
			aBQ <= 0;
            state <= Read;
            ramAQ <= 0;
            ramBQ <= 0;
        end
        else begin
            multQ <= multD;
            ramAQ <= ramAD;
            ramBQ <= ramBD;
			aAQ <= aAD;
			aBQ <= aBD;
			counter2Q <= counter2D;
			partialQ<=partialD;
			counterQ<=counterD;
            state <= nextState;
        end
    end
    
endmodule

Verilog Project/ESE 461/pipe report/pipe_tb.v
`timescale 1ns / 1ps

module pipe_tb();

    reg  [15:0] a;
    reg  [15:0] b;
    reg  clk;
    reg  reset;
    reg [3:0] wrAddr;
    reg [5:0] i;
    reg [5:0] j;
    reg [15:0] A1[11:0];
    reg [15:0] B1[11:0];

    wire [15:0] product;
    parameter clk_period = 20;
	//A = [ 1.25, 2.5, 2.5, 2, 3, 2, 1.25, 3.5, 4.5, 2]
	//B = [ 1.5, 1.5, 5, 2, 5, 3, 3.5, 5, 4, 3]


    pipe nopipe(
        .clk(clk),
        .reset(reset),
        .A(a),
        .B(b),
        .wrAddr(wrAddr),
        .result(product)
        );

    initial
    begin
        $dumpfile("pipe.vcd");
        $dumpvars(0, pipe_tb);
        A1[0]=16'h0140;
        A1[1]=16'h0280;
        A1[2]=16'h0280;
        A1[3]=16'h0200;
        A1[4]=16'h0300;
        A1[5]=16'h0200;
        A1[6]=16'h0140;
        A1[7]=16'h0380;
        A1[8]=16'h0480;
        A1[9]=16'h0200;
        A1[10]=16'h0000;
        A1[11]=16'h0000;
        
        B1[0]=16'h0180;
        B1[1]=16'h0180;
        B1[2]=16'h0500;
        B1[3]=16'h0200;
        B1[4]=16'h0500;
        B1[5]=16'h0300;
        B1[6]=16'h0380;
        B1[7]=16'h0500;
        B1[8]=16'h0400;
        B1[9]=16'h0300;
        B1[10]=16'h0000;
        B1[11]=16'h0000;

//        $readmemh("H:/ESE461/lab3/a1.tb",A1);
//        $readmemh("H:/ESE461/lab3/b1.tb",B1);

        reset = 1;
        clk = 0;
        a = 0;
        b = 0;
        wrAddr = 0;

        // 1
        #(clk_period*3)
        reset = 0;
        wrAddr = 2;
        #(clk_period)
        for(i=0;i<12;i=i+1)begin
            wrAddr = 1;
            a = A1[i];
            b = B1[i];
            #(clk_period)
            wrAddr = 0;
            #(clk_period*62);
        end
		
        $finish;
    end

    always 
        #10 clk = !clk;

endmodule

ESE 461/pipe report/pipe.vcd
$date
	Fri Nov 23 14:55:16 2018
$end

$version
	Synopsys VCS version J-2014.12-SP1-1_Full64
$end

$timescale
	1ps
$end

$comment Csum: 1 516b0413ee652eaf $end


$scope module pipe_tb $end
$var reg 16 ! a [15:0] $end
$var reg 16 " b [15:0] $end
$var reg 1 # clk $end
$var reg 1 $ reset $end
$var reg 4 % wrAddr [3:0] $end
$var reg 6 & i [5:0] $end
$var reg 6 ' j [5:0] $end
$var wire 16 ( product [15:0] $end

$scope module nopipe $end
$var wire 1 # clk $end
$var wire 1 $ reset $end
$var wire 4 % wrAddr [3:0] $end
$var wire 16 ! A [15:0] $end
$var wire 16 " B [15:0] $end
$var reg 16 ( result [15:0] $end
$var wire 16 ) result2 [15:0] $end
$var reg 1 * weA $end
$var reg 9 + aAD [8:0] $end
$var reg 9 , aAQ [8:0] $end
$var wire 16 - doA [15:0] $end
$var reg 1 . weB $end
$var reg 9 / aBD [8:0] $end
$var reg 9 0 aBQ [8:0] $end
$var wire 16 1 doB [15:0] $end
$var reg 1 2 rd $end
$var reg 1 3 md $end
$var reg 16 4 ramAD [15:0] $end
$var reg 16 5 ramAQ [15:0] $end
$var reg 16 6 ramBD [15:0] $end
$var reg 16 7 ramBQ [15:0] $end
$var reg 16 8 multD [15:0] $end
$var reg 16 9 multQ [15:0] $end
$var reg 16 : partialD [15:0] $end
$var reg 16 ; partialQ [15:0] $end
$var reg 16 < counterD [15:0] $end
$var reg 16 = counterQ [15:0] $end
$var reg 16 > counter2D [15:0] $end
$var reg 16 ? counter2Q [15:0] $end
$var reg 2 @ state [1:0] $end
$var reg 2 A nextState [1:0] $end
$var reg 1 B done $end

$scope module ramA $end
$var wire 1 # clk $end
$var wire 1 * we $end
$var wire 6 C a [5:0] $end
$var wire 16 ! di [15:0] $end
$var wire 16 D do [15:0] $end
$var integer 32 E i $end
$upscope $end


$scope module ramB $end
$var wire 1 # clk $end
$var wire 1 . we $end
$var wire 6 F a [5:0] $end
$var wire 16 " di [15:0] $end
$var wire 16 G do [15:0] $end
$var integer 32 H i $end
$upscope $end


$scope module mult $end
$var wire 1 # clk $end
$var wire 1 $ reset $end
$var wire 16 5 A [15:0] $end
$var wire 16 7 B [15:0] $end
$var reg 16 I PRODUCT [15:0] $end
$var reg 32 J storeD [31:0] $end
$var reg 32 K storeQ [31:0] $end
$var reg 16 L storeBD [15:0] $end
$var reg 16 M storeBQ [15:0] $end
$var reg 32 N productD [31:0] $end
$var reg 32 O productQ [31:0] $end
$var reg 4 P nextState [3:0] $end
$var reg 4 Q state [3:0] $end
$var reg 7 R counterD [6:0] $end
$var reg 7 S counterQ [6:0] $end
$upscope $end

$upscope $end

$upscope $end

$enddefinitions $end

#0
$dumpvars
0#
1B
03
02
1$
0*
0.
bxxxxxxxxxxxxxxxx I
b0000000000000000 !
bxxxxxxxxx +
bxxxxxxxxx ,
bxxxxxxxxx /
bxxxxxxxxx 0
b0000000000000000 "
b0000000000000000 >
bxxxxxxxxxxxxxxxx ?
bxxxxxxxxxxxxxxxx <
bxxxxxxxxxxxxxxxx =
bxxxxxxxxxxxxxxxx -
bxxxxxxxxxxxxxxxx 1
bxxxxxxxxxxxxxxxx D
bxxxxxx &
bxxxxxx '
bxxxxxxxxxxxxxxxx 8
bxxxxxxxxxxxxxxxx 9
bxxxxxxx R
bxxxxxxx S
bxxxx P
bxxxx Q
b00 A
b00000000000000000000000000001010 E
bxxxxxxxxxxxxxxxx :
bxxxxxxxxxxxxxxxx ;
bxxxxxxxxxxxxxxxxxxxxxxxxxxxxxxxx N
bxxxxxxxxxxxxxxxxxxxxxxxxxxxxxxxx O
bxxxxxxxxxxxxxxxx 4
bxxxxxxxxxxxxxxxx 5
bxxxxxxxxxxxxxxxx 6
bxxxxxxxxxxxxxxxx 7
bxxxxxxxxxxxxxxxx G
b00000000000000000000000000001010 H
bxxxxxxxxxxxxxxxx (
bxxxxxxxxxxxxxxxx )
bxx @
bxxxxxxxxxxxxxxxx L
bxxxxxxxxxxxxxxxx M
bxxxxxxxxxxxxxxxxxxxxxxxxxxxxxxxx J
bxxxxxxxxxxxxxxxxxxxxxxxxxxxxxxxx K
bxxxxxx C
bxxxxxx F
b0000 %
$end
#10000
1#
b0000000000000000 9
b0000000000000000 5
b0000000000000000 7
b000000000 ,
b000000 C
b0000000000000000 D
b0000000000000000 -
b000000000 0
b000000 F
b0000000000000000 G
b0000000000000000 1
b0000000000000000 ?
b0000000000000000 ;
b0000000000000000 =
b00 @
b0000000 S
b00000000000000000000000000000000 K
b0000000000000000 M
b00000000000000000000000000000000 O
b0000 Q
b000000000 /
b000000000 +
b0000000000000000 <
b0000000000000000 8
b0000000000000000 6
b0000000000000000 4
b0000000000000000 :
b0001 P
b0000000 R
b00000000000000000000000000000000 N
b0000000000000000 L
b00000000000000000000000000000000 J
#20000
0#
#30000
1#
#40000
0#
#50000
1#
#60000
0$
b0010 %
0#
#70000
1#
b0001 Q
b0000001 R
#80000
b000000 &
b0001 %
b0000000101000000 !
b0000000110000000 "
0#
b11 A
1.
1*
#90000
1#
b11 @
b0000001 S
b0000000101000000 D
b0000000101000000 -
b0000000110000000 G
b0000000110000000 1
b01 A
b0000000110000000 6
b0000000101000000 4
b000000001 /
b000000001 +
b0000010 R
#100000
b0000 %
0#
#110000
1#
b0000000101000000 5
b0000000110000000 7
b000000001 ,
b000001 C
b0000000000000000 D
b0000000000000000 -
b000000001 0
b000001 F
b0000000000000000 G
b0000000000000000 1
b01 @
b0000010 S
0.
0*
b10 A
b0000000000000001 <
bxxxxxxxxxxxxxxxx 8
b0000011 R
#120000
0#
#130000
1#
bxxxxxxxxxxxxxxxx 9
b0000000000000001 =
b10 @
b0000011 S
b00 A
b0000000000000000 (
b0000100 R
#140000
0#
#150000
1#
b00 @
b0000100 S
b0000101 R
#160000
0#
#170000
1#
b0000101 S
b0000110 R
#180000
0#
#190000
1#
b0000110 S
b0000111 R
#200000
0#
#210000
1#
b0000111 S
b0001000 R
b00000000000000001010000000000000 J
#220000
0#
#230000
1#
b0001000 S
b00000000000000001010000000000000 K
b0001001 R
b00000000000000001010000000000000 N
b00000000000000010100000000000000 J
#240000
0#
#250000
1#
b0001001 S
b00000000000000010100000000000000 K
b00000000000000001010000000000000 O
b0001010 R
#260000
0#
#270000
1#
b0001010 S
b0001011 R
#280000
0#
#290000
1#
b0001011 S
b0001100 R
#300000
0#
#310000
1#
b0001100 S
b0001101 R
#320000
0#
#330000
1#
b0001101 S
b0001110 R
#340000
0#
#350000
1#
b0001110 S
b0001111 R
#360000
0#
#370000
1#
b0001111 S
b0010000 R
#380000
0#
#390000
1#
b0010000 S
b0010001 R
#400000
0#
#410000
1#
b0010001 S
b0010010 R
#420000
0#
#430000
1#
b0010010 S
b0010011 R
#440000
0#
#450000
1#
b0010011 S
b0010100 R
#460000
0#
#470000
1#
b0010100 S
b0010101 R
#480000
0#
#490000
1#
b0010101 S
b0010110 R
#500000
0#
#510000
1#
b0010110 S
b0010111 R
#520000
0#
#530000
1#
b0010111 S
b0011000 R
#540000
0#
#550000
1#
b0011000 S
b0011001 R
#560000
0#
#570000
1#
b0011001 S
b0011010 R
#580000
0#
#590000
1#
b0011010 S
b0011011 R
#600000
0#
#610000
1#
b0011011 S
b0011100 R
#620000
0#
#630000
1#
b0011100 S
b0011101 R
#640000
0#
#650000
1#
b0011101 S
b0011110 R
#660000
0#
#670000
1#
b0011110 S
b0011111 R
#680000
0#
#690000
1#
b0011111 S
b0100000 R
#700000
0#
#710000
1#
b0100000 S
b0010 P
b00000000000000011110000000000000 N
#720000
0#
#730000
1#
b00000000000000011110000000000000 O
b0010 Q
b0000 P
b0000000111100000 I
b0000000111100000 )
#740000
0#
#750000
1#
b0000 Q
b0001 P
b0000000 R
b00000000000000000000000000000000 N
b0000000110000000 L
b00000000000000000000000000000000 J
#760000
0#
#770000
1#
b0000000 S
b00000000000000000000000000000000 K
b0000000110000000 M
b00000000000000000000000000000000 O
b0001 Q
b0000001 R
#780000
0#
#790000
1#
b0000001 S
b0000010 R
#800000
0#
#810000
1#
b0000010 S
b0000011 R
#820000
0#
#830000
1#
b0000011 S
b0000100 R
#840000
0#
#850000
1#
b0000100 S
b0000101 R
#860000
0#
#870000
1#
b0000101 S
b0000110 R
#880000
0#
#890000
1#
b0000110 S
b0000111 R
#900000
0#
#910000
1#
b0000111 S
b0001000 R
b00000000000000001010000000000000 J
#920000
0#
#930000
1#
b0001000 S
b00000000000000001010000000000000 K
b0001001 R
b00000000000000001010000000000000 N
b00000000000000010100000000000000 J
#940000
0#
#950000
1#
b0001001 S
b00000000000000010100000000000000 K
b00000000000000001010000000000000 O
b0001010 R
#960000
0#
#970000
1#
b0001010 S
b0001011 R
#980000
0#
#990000
1#
b0001011 S
b0001100 R
#1000000
0#
#1010000
1#
b0001100 S
b0001101 R
#1020000
0#
#1030000
1#
b0001101 S
b0001110 R
#1040000
0#
#1050000
1#
b0001110 S
b0001111 R
#1060000
0#
#1070000
1#
b0001111 S
b0010000 R
#1080000
0#
#1090000
1#
b0010000 S
b0010001 R
#1100000
0#
#1110000
1#
b0010001 S
b0010010 R
#1120000
0#
#1130000
1#
b0010010 S
b0010011 R
#1140000
0#
#1150000
1#
b0010011 S
b0010100 R
#1160000
0#
#1170000
1#
b0010100 S
b0010101 R
#1180000
0#
#1190000
1#
b0010101 S
b0010110 R
#1200000
0#
#1210000
1#
b0010110 S
b0010111 R
#1220000
0#
#1230000
1#
b0010111 S
b0011000 R
#1240000
0#
#1250000
1#
b0011000 S
b0011001 R
#1260000
0#
#1270000
1#
b0011001 S
b0011010 R
#1280000
0#
#1290000
1#
b0011010 S
b0011011 R
#1300000
0#
#1310000
1#
b0011011 S
b0011100 R
#1320000
0#
#1330000
1#
b0011100 S
b0011101 R
#1340000
b000001 &
b0001 %
b0000001010000000 !
0#
b11 A
1.
1*
#1350000
1#
b11 @
b0011101 S
b0000001010000000 D
b0000001010000000 -
b0000000110000000 G
b0000000110000000 1
b01 A
b0000001010000000 4
b000000010 /
b000000010 +
b0011110 R
#1360000
b0000 %
0#
#1370000
1#
b0000001010000000 5
b000000010 ,
b000010 C
b0000000000000000 D
b0000000000000000 -
b000000010 0
b000010 F
b0000000000000000 G
b0000000000000000 1
b01 @
b0011110 S
0.
0*
b10 A
b0000000000000010 <
b0000000111100000 8
b0011111 R
#1380000
0#
#1390000
1#
b0000000111100000 9
b0000000000000010 =
b10 @
b0011111 S
b00 A
b0100000 R
#1400000
0#
#1410000
1#
b00 @
b0100000 S
b0010 P
b00000000000000011110000000000000 N
#1420000
0#
#1430000
1#
b00000000000000011110000000000000 O
b0010 Q
b0000 P
#1440000
0#
#1450000
1#
b0000 Q
b0001 P
b0000000 R
b00000000000000000000000000000000 N
b00000000000000000000000000000000 J
#1460000
0#
#1470000
1#
b0000000 S
b00000000000000000000000000000000 K
b00000000000000000000000000000000 O
b0001 Q
b0000001 R
#1480000
0#
#1490000
1#
b0000001 S
b0000010 R
#1500000
0#
#1510000
1#
b0000010 S
b0000011 R
#1520000
0#
#1530000
1#
b0000011 S
b0000100 R
#1540000
0#
#1550000
1#
b0000100 S
b0000101 R
#1560000
0#
#1570000
1#
b0000101 S
b0000110 R
#1580000
0#
#1590000
1#
b0000110 S
b0000111 R
#1600000
0#
#1610000
1#
b0000111 S
b0001000 R
b00000000000000010100000000000000 J
#1620000
0#
#1630000
1#
b0001000 S
b00000000000000010100000000000000 K
b0001001 R
b00000000000000010100000000000000 N
b00000000000000101000000000000000 J
#1640000
0#
#1650000
1#
b0001001 S
b00000000000000101000000000000000 K
b00000000000000010100000000000000 O
b0001010 R
#1660000
0#
#1670000
1#
b0001010 S
b0001011 R
#1680000
0#
#1690000
1#
b0001011 S
b0001100 R
#1700000
0#
#1710000
1#
b0001100 S
b0001101 R
#1720000
0#
#1730000
1#
b0001101 S
b0001110 R
#1740000
0#
#1750000
1#
b0001110 S
b0001111 R
#1760000
0#
#1770000
1#
b0001111 S
b0010000 R
#1780000
0#
#1790000
1#
b0010000 S
b0010001 R
#1800000
0#
#1810000
1#
b0010001 S
b0010010 R
#1820000
0#
#1830000
1#
b0010010 S
b0010011 R
#1840000
0#
#1850000
1#
b0010011 S
b0010100 R
#1860000
0#
#1870000
1#
b0010100 S
b0010101 R
#1880000
0#
#1890000
1#
b0010101 S
b0010110 R
#1900000
0#
#1910000
1#
b0010110 S
b0010111 R
#1920000
0#
#1930000
1#
b0010111 S
b0011000 R
#1940000
0#
#1950000
1#
b0011000 S
b0011001 R
#1960000
0#
#1970000
1#
b0011001 S
b0011010 R
#1980000
0#
#1990000
1#
b0011010 S
b0011011 R
#2000000
0#
#2010000
1#
b0011011 S
b0011100 R
#2020000
0#
#2030000
1#
b0011100 S
b0011101 R
#2040000
0#
#2050000
1#
b0011101 S
b0011110 R
#2060000
0#
#2070000
1#
b0011110 S
b0011111 R
#2080000
0#
#2090000
1#
b0011111 S
b0100000 R
#2100000
0#
#2110000
1#
b0100000 S
b0010 P
b00000000000000111100000000000000 N
#2120000
0#
#2130000
1#
b00000000000000111100000000000000 O
b0010 Q
b0000 P
b0000001111000000 I
b0000001111000000 )
#2140000
0#
#2150000
1#
b0000 Q
b0001 P
b0000000 R
b00000000000000000000000000000000 N
b00000000000000000000000000000000 J
#2160000
0#
#2170000
1#
b0000000 S
b00000000000000000000000000000000 K
b00000000000000000000000000000000 O
b0001 Q
b0000001 R
#2180000
0#
#2190000
1#
b0000001 S
b0000010 R
#2200000
0#
#2210000
1#
b0000010 S
b0000011 R
#2220000
0#
#2230000
1#
b0000011 S
b0000100 R
#2240000
0#
#2250000
1#
b0000100 S
b0000101 R
#2260000
0#
#2270000
1#
b0000101 S
b0000110 R
#2280000
0#
#2290000
1#
b0000110 S
b0000111 R
#2300000
0#
#2310000
1#
b0000111 S
b0001000 R
b00000000000000010100000000000000 J
#2320000
0#
#2330000
1#
b0001000 S
b00000000000000010100000000000000 K
b0001001 R
b00000000000000010100000000000000 N
b00000000000000101000000000000000 J
#2340000
0#
#2350000
1#
b0001001 S
b00000000000000101000000000000000 K
b00000000000000010100000000000000 O
b0001010 R
#2360000
0#
#2370000
1#
b0001010 S
b0001011 R
#2380000
0#
#2390000
1#
b0001011 S
b0001100 R
#2400000
0#
#2410000
1#
b0001100 S
b0001101 R
#2420000
0#
#2430000
1#
b0001101 S
b0001110 R
#2440000
0#
#2450000
1#
b0001110 S
b0001111 R
#2460000
0#
#2470000
1#
b0001111 S
b0010000 R
#2480000
0#
#2490000
1#
b0010000 S
b0010001 R
#2500000
0#
#2510000
1#
b0010001 S
b0010010 R
#2520000
0#
#2530000
1#
b0010010 S
b0010011 R
#2540000
0#
#2550000
1#
b0010011 S
b0010100 R
#2560000
0#
#2570000
1#
b0010100 S
b0010101 R
#2580000
0#
#2590000
1#
b0010101 S
b0010110 R
#2600000
b000010 &
b0001 %
b0000010100000000 "
0#
b11 A
1.
1*
#2610000
1#
b11 @
b0010110 S
b0000001010000000 D
b0000001010000000 -
b0000010100000000 G
b0000010100000000 1
b01 A
b0000010100000000 6
b000000011 /
b000000011 +
b0010111 R
#2620000
b0000 %
0#
#2630000
1#
b0000010100000000 7
b000000011 ,
b000011 C
b0000000000000000 D
b0000000000000000 -
b000000011 0
b000011 F
b0000000000000000 G
b0000000000000000 1
b01 @
b0010111 S
0.
0*
b10 A
b0000000000000011 <
b0000001111000000 8
b0000000111100000 :
b0011000 R
#2640000
0#
#2650000
1#
b0000001111000000 9
b0000000111100000 ;
b0000000000000011 =
b10 @
b0011000 S
b00 A
b0000000111100000 (
b0011001 R
#2660000
0#
#2670000
1#
b00 @
b0011001 S
b0011010 R
#2680000
0#
#2690000
1#
b0011010 S
b0011011 R
#2700000
0#
#2710000
1#
b0011011 S
b0011100 R
#2720000
0#
#2730000
1#
b0011100 S
b0011101 R
#2740000
0#
#2750000
1#
b0011101 S
b0011110 R
#2760000
0#
#2770000
1#
b0011110 S
b0011111 R
#2780000
0#
#2790000
1#
b0011111 S
b0100000 R
#2800000
0#
#2810000
1#
b0100000 S
b0010 P
b00000000000000111100000000000000 N
#2820000
0#
#2830000
1#
b00000000000000111100000000000000 O
b0010 Q
b0000 P
#2840000
0#
#2850000
1#
b0000 Q
b0001 P
b0000000 R
b00000000000000000000000000000000 N
b0000010100000000 L
b00000000000000000000000000000000 J
#2860000
0#
#2870000
1#
b0000000 S
b00000000000000000000000000000000 K
b0000010100000000 M
b00000000000000000000000000000000 O
b0001 Q
b0000001 R
#2880000
0#
#2890000
1#
b0000001 S
b0000010 R
#2900000
0#
#2910000
1#
b0000010 S
b0000011 R
#2920000
0#
#2930000
1#
b0000011 S
b0000100 R
#2940000
0#
#2950000
1#
b0000100 S
b0000101 R
#2960000
0#
#2970000
1#
b0000101 S
b0000110 R
#2980000
0#
#2990000
1#
b0000110 S
b0000111 R
#3000000
0#
#3010000
1#
b0000111 S
b0001000 R
#3020000
0#
#3030000
1#
b0001000 S
b0001001 R
b00000000000000101000000000000000 J
#3040000
0#
#3050000
1#
b0001001 S
b00000000000000101000000000000000 K
b0001010 R
#3060000
0#
#3070000
1#
b0001010 S
b0001011 R
b00000000000000101000000000000000 N
b00000000000010100000000000000000 J
#3080000
0#
#3090000
1#
b0001011 S
b00000000000010100000000000000000 K
b00000000000000101000000000000000 O
b0001100 R
#3100000
0#
#3110000
1#
b0001100 S
b0001101 R
#3120000
0#
#3130000
1#
b0001101 S
b0001110 R
#3140000
0#
#3150000
1#
b0001110 S
b0001111 R
#3160000
0#
#3170000
1#
b0001111 S
b0010000 R
#3180000
0#
#3190000
1#
b0010000 S
b0010001 R
#3200000
0#
#3210000
1#
b0010001 S
b0010010 R
#3220000
0#
#3230000
1#
b0010010 S
b0010011 R
#3240000
0#
#3250000
1#
b0010011 S
b0010100 R
#3260000
0#
#3270000
1#
b0010100 S
b0010101 R
#3280000
0#
#3290000
1#
b0010101 S
b0010110 R
#3300000
0#
#3310000
1#
b0010110 S
b0010111 R
#3320000
0#
#3330000
1#
b0010111 S
b0011000 R
#3340000
0#
#3350000
1#
b0011000 S
b0011001 R
#3360000
0#
#3370000
1#
b0011001 S
b0011010 R
#3380000
0#
#3390000
1#
b0011010 S
b0011011 R
#3400000
0#
#3410000
1#
b0011011 S
b0011100 R
#3420000
0#
#3430000
1#
b0011100 S
b0011101 R
#3440000
0#
#3450000
1#
b0011101 S
b0011110 R
#3460000
0#
#3470000
1#
b0011110 S
b0011111 R
#3480000
0#
#3490000
1#
b0011111 S
b0100000 R
#3500000
0#
#3510000
1#
b0100000 S
b0010 P
b00000000000011001000000000000000 N
#3520000
0#
#3530000
1#
b00000000000011001000000000000000 O
b0010 Q
b0000 P
b0000110010000000 I
b0000110010000000 )
#3540000
0#
#3550000
1#
b0000 Q
b0001 P
b0000000 R
b00000000000000000000000000000000 N
b00000000000000000000000000000000 J
#3560000
0#
#3570000
1#
b0000000 S
b00000000000000000000000000000000 K
b00000000000000000000000000000000 O
b0001 Q
b0000001 R
#3580000
0#
#3590000
1#
b0000001 S
b0000010 R
#3600000
0#
#3610000
1#
b0000010 S
b0000011 R
#3620000
0#
#3630000
1#
b0000011 S
b0000100 R
#3640000
0#
#3650000
1#
b0000100 S
b0000101 R
#3660000
0#
#3670000
1#
b0000101 S
b0000110 R
#3680000
0#
#3690000
1#
b0000110 S
b0000111 R
#3700000
0#
#3710000
1#
b0000111 S
b0001000 R
#3720000
0#
#3730000
1#
b0001000 S
b0001001 R
b00000000000000101000000000000000 J
#3740000
0#
#3750000
1#
b0001001 S
b00000000000000101000000000000000 K
b0001010 R
#3760000
0#
#3770000
1#
b0001010 S
b0001011 R
b00000000000000101000000000000000 N
b00000000000010100000000000000000 J
#3780000
0#
#3790000
1#
b0001011 S
b00000000000010100000000000000000 K
b00000000000000101000000000000000 O
b0001100 R
#3800000
0#
#3810000
1#
b0001100 S
b0001101 R
#3820000
0#
#3830000
1#
b0001101 S
b0001110 R
#3840000
0#
#3850000
1#
b0001110 S
b0001111 R
#3860000
b000011 &
b0001 %
b0000001000000000 !
b0000001000000000 "
0#
b11 A
1.
1*
#3870000
1#
b11 @
b0001111 S
b0000001000000000 D
b0000001000000000 -
b0000001000000000 G
b0000001000000000 1
b01 A
b0000001000000000 6
b0000001000000000 4
b000000100 /
b000000100 +
b0010000 R
#3880000
b0000 %
0#
#3890000
1#
b0000001000000000 5
b0000001000000000 7
b000000100 ,
b000100 C
b0000000000000000 D
b0000000000000000 -
b000000100 0
b000100 F
b0000000000000000 G
b0000000000000000 1
b01 @
b0010000 S
0.
0*
b10 A
b0000000000000100 <
b0000110010000000 8
b0000010110100000 :
b0010001 R
#3900000
0#
#3910000
1#
b0000110010000000 9
b0000010110100000 ;
b0000000000000100 =
b10 @
b0010001 S
b00 A
b0000010110100000 (
b0010010 R
#3920000
0#
#3930000
1#
b00 @
b0010010 S
b0010011 R
#3940000
0#
#3950000
1#
b0010011 S
b0010100 R
#3960000
0#
#3970000
1#
b0010100 S
b0010101 R
#3980000
0#
#3990000
1#
b0010101 S
b0010110 R
#4000000
0#
#4010000
1#
b0010110 S
b0010111 R
#4020000
0#
#4030000
1#
b0010111 S
b0011000 R
#4040000
0#
#4050000
1#
b0011000 S
b0011001 R
#4060000
0#
#4070000
1#
b0011001 S
b0011010 R
#4080000
0#
#4090000
1#
b0011010 S
b0011011 R
#4100000
0#
#4110000
1#
b0011011 S
b0011100 R
#4120000
0#
#4130000
1#
b0011100 S
b0011101 R
#4140000
0#
#4150000
1#
b0011101 S
b0011110 R
#4160000
0#
#4170000
1#
b0011110 S
b0011111 R
#4180000
0#
#4190000
1#
b0011111 S
b0100000 R
#4200000
0#
#4210000
1#
b0100000 S
b0010 P
b00000000000011001000000000000000 N
#4220000
0#
#4230000
1#
b00000000000011001000000000000000 O
b0010 Q
b0000 P
#4240000
0#
#4250000
1#
b0000 Q
b0001 P
b0000000 R
b00000000000000000000000000000000 N
b0000001000000000 L
b00000000000000000000000000000000 J
#4260000
0#
#4270000
1#
b0000000 S
b00000000000000000000000000000000 K
b0000001000000000 M
b00000000000000000000000000000000 O
b0001 Q
b0000001 R
#4280000
0#
