ESE 461/pipe report/mult.v
module mult( clk, reset, A, B, PRODUCT);

  input clk;
  input reset;

  input [15 : 0] A;
  input [15 : 0] B;
  output reg[15 : 0] PRODUCT;
  
  // Your code begins here
  reg [31:0] storeD, storeQ;
  reg [15:0] storeBD, storeBQ;
  reg [31:0] productD, productQ;
  reg [3:0] nextState, state;
  reg [6:0] counterD, counterQ;
  parameter init = 0,  step1 = 1,step2 = 2;
  //combination code and fsm
  //A muliplicand, and B is mulitplier
   always @ * begin
   storeD = storeQ;
   productD = productQ;
   storeBD = storeBQ;
   counterD = counterQ;
   nextState = state;
   
        case(state)
            init: begin
                storeD = 0;
                storeBD = B;
                productD = 0;
                counterD = 0;
                nextState = step1; 
            end
            
        step1: begin
           if(counterD < 32)begin
                if(B[counterQ]==1)begin
                    storeD = A << counterQ;
                    productD = productQ + storeQ;
                    counterD = counterQ + 1;
                end
                else begin
                    counterD = counterQ + 1;
                end
           end
           else begin
                productD = productQ + storeQ;
                nextState = step2;
           end
        end
        
        step2 : begin
              PRODUCT[7:0] = productQ[15:8];
              PRODUCT[15:8] = productQ[23:16];
              nextState = init;
        end
        endcase
   end
   
   //sequential logic
   always @ (posedge clk) begin
        if ( reset ) begin
            storeQ <= 0;
            counterQ <= 0;
            productQ <= 0;
            storeBQ <= 0;
            state <= init;
            
        end else begin
            counterQ <= counterD;
            storeQ <= storeD;
            storeBQ <= storeBD;
            productQ <= productD;
            state <= nextState;
        end
   end
endmodule

ESE 461/nopipe report/ramB.v
`timescale 1ns / 1ps
//////////////////////////////////////////////////////////////////////////////////

//////////////////////////////////////////////////////////////////////////////////


               

module ramB (clk, we, a, di, do);
    input clk;
    input we;
    input [5:0] a;
    input [15:0] di;
    output [15:0] do;
    reg [15:0] ram [9:0];
    integer i = 0;

    initial begin
    for(i=0; i<10 ; i=i+1)begin
       ram[i]<=16'b0;
    end
    end
    
    always @(posedge clk) begin    
        if (we) 
            ram[a] <= di;
        end


    assign do = ram[a];
    
endmodule

ESE 461/nopipe report/ramA.v
`timescale 1ns / 1ps
//////////////////////////////////////////////////////////////////////////////////

//////////////////////////////////////////////////////////////////////////////////


module ramA (clk, we, a, di, do);
    input clk;
    input we;
    input [5:0] a;
    input [15:0] di;
    output [15:0] do;
    reg [15:0] ram [9:0];
    integer i = 0;

    initial begin
    for(i=0; i<10 ; i=i+1)begin
       ram[i]<=16'b0;
    end
    end
    
    always @(posedge clk) begin    
        if (we)
            ram[a] <= di;
        end

    assign do = ram[a];
    
endmodule

ESE 461/nopipe report/nopipe.v
`timescale 1ns / 1ps
//////////////////////////////////////////////////////////////////////////////////

// 
//////////////////////////////////////////////////////////////////////////////////


module nopipe (clk, reset, A,B, result, wrAddr);
	
	input clk;
	input reset;
	input wire [3:0] wrAddr;
  
	input [15:0] A;
	input [15:0] B;
	output reg [15:0] result;
	
	wire [15:0] result2;
	
	reg weA;
    reg [8:0] aAD;
    reg [8:0] aAQ;
    wire signed [15:0] doA;
  
	ramA rA(
	.clk(clk),
	.we(weA),
	.a(aAQ),
	.di(A),
	.do(doA)
	);
	
 	reg weB;
    reg [8:0] aBD;
    reg [8:0] aBQ;
    wire signed [15:0] doB; 
    
    reg rd,md;

	ramB rB(
	.clk(clk),
	.we(weB),
	.a(aBQ),
	.di(B),
	.do(doB)
	);  
	
	mult mult(
	.clk(clk),
	.reset(reset),
	.A(doA),
	.B(doB),
	.PRODUCT(result2)
	);

	//Registers   
 
    reg [15:0] partialD, partialQ;
	reg [15:0] counterD, counterQ;
	reg [15:0] counter2D, counter2Q;

     
	//state machine
    
    reg [1:0] state, nextState;
    parameter Read=0, Mult=1,Fresult=2;
    reg done;
    
    always @ * begin
		partialD = partialQ;
		counter2D = 0;
		weA=0;
		weB=0;
		done=1;
		nextState=state;
		aAD = aAQ;
		aBD = aBQ;
		rd = 0;
		md = 0;
    
        case (state)
       
            Read : begin
                //Reset registers
	              if(wrAddr == 2) begin
                    aAD = 0;
                    aBD = 0;
                    partialD = 0;
                    counterD = 0;
                    nextState = Read;
                  end
                  if(wrAddr == 1) begin
                        weA = 1;    
                        weB = 1;
                        if(aAQ <9 && aBQ <9)begin
                            aAD =aAQ +1;
                            aBD =aBQ +1;
                        end else begin
                            nextState = Mult;   
                            aAD = 0;
                            aBD = 0;
                        end     
                  end
            end
            Mult : begin
                    counter2D = counter2Q + 1;
                    if(counter2Q == 78)begin
                        counter2D = 0;
                        counterD = counterQ + 1;
                        if(counterQ <10) begin
                           partialD = partialQ + result2;
                           aAD =aAQ +1;
                           aBD =aBQ +1;
                        end else begin
                           nextState = Fresult;
                           counterD = 0;
                        end
                    end else begin
                        nextState = Mult;
                    end
			end
			Fresult: begin
				result = partialQ;				
			    nextState = Read;
			end

            default : begin
                nextState = Read;
            end
        endcase
    end
  
	
	//Sequential logic
	always @ (posedge clk) begin
        if (reset) begin
			partialQ <=0;
			counterQ <=0;
			counter2Q <=0;
			aAQ <=0;
			aBQ <= 0;
            state <= Read;
        end
        else begin
			aAQ <= aAD;
			aBQ <= aBD;
			counter2Q <= counter2D;
			partialQ<=partialD;
			counterQ<=counterD;
            state <= nextState;
        end
    end
    
endmodule

Verilog Project/ESE 461/nopipe report/nopipe_tb.v
`timescale 1ns / 1ps

module nopipe_tb();

    reg  [15:0] a;
    reg  [15:0] b;
    reg  clk;
    reg  reset;
    reg [3:0] wrAddr;
    reg [5:0] i;
    reg [5:0] j;
    reg [15:0] A1[9:0];
    reg [15:0] B1[9:0];

    wire [15:0] product;
    parameter clk_period = 20;
	//A = [ 1.25, 2.5, 2.5, 2, 3, 2, 1.25, 3.5, 4.5, 2]
	//B = [ 1.5, 1.5, 5, 2, 5, 3, 3.5, 5, 4, 3]


    nopipe nopipe(
        .clk(clk),
        .reset(reset),
        .A(a),
        .B(b),
        .wrAddr(wrAddr),
        .result(product)
        );

    initial
    begin
        $dumpfile("nopipe.vcd");
        $dumpvars(0, nopipe_tb);
A1[0]=16'h0140;
A1[1]=16'h0280;
A1[2]=16'h0280;
A1[3]=16'h0200;
A1[4]=16'h0300;
A1[5]=16'h0200;
A1[6]=16'h0140;
A1[7]=16'h0380;
A1[8]=16'h0480;
A1[9]=16'h0200;

B1[0]=16'h0180;
B1[1]=16'h0180;
B1[2]=16'h0500;
B1[3]=16'h0200;
B1[4]=16'h0500;
B1[5]=16'h0300;
B1[6]=16'h0380;
B1[7]=16'h0500;
B1[8]=16'h0400;
B1[9]=16'h0300;



        reset = 1;
        clk = 0;
        a = 0;
        b = 0;
        wrAddr = 0;

        // 1
        #(clk_period*3)
        reset = 0;
        wrAddr = 2;
        #(clk_period)
        for(i=0;i<10;i=i+1)begin
            wrAddr = 1;
            a = A1[i];
            b = B1[i];
            #(clk_period)
            wrAddr = 0;
            #(clk_period*5);
        end
		
        $finish;
    end

    always 
        #10 clk = !clk;

endmodule

ESE 461/nopipe report/nopipe.vcd
$date
	Fri Nov 23 14:47:44 2018
$end

$version
	Synopsys VCS version J-2014.12-SP1-1_Full64
$end

$timescale
	1ps
$end

$comment Csum: 1 be323c5c7b58317d $end


$scope module nopipe_tb $end
$var reg 16 ! a [15:0] $end
$var reg 16 " b [15:0] $end
$var reg 1 # clk $end
$var reg 1 $ reset $end
$var reg 4 % wrAddr [3:0] $end
$var reg 6 & i [5:0] $end
$var reg 6 ' j [5:0] $end
$var wire 16 ( product [15:0] $end

$scope module nopipe $end
$var wire 1 # clk $end
$var wire 1 $ reset $end
$var wire 4 % wrAddr [3:0] $end
$var wire 16 ! A [15:0] $end
$var wire 16 " B [15:0] $end
$var reg 16 ( result [15:0] $end
$var wire 16 ) result2 [15:0] $end
$var reg 1 * weA $end
$var reg 9 + aAD [8:0] $end
$var reg 9 , aAQ [8:0] $end
$var wire 16 - doA [15:0] $end
$var reg 1 . weB $end
$var reg 9 / aBD [8:0] $end
$var reg 9 0 aBQ [8:0] $end
$var wire 16 1 doB [15:0] $end
$var reg 1 2 rd $end
$var reg 1 3 md $end
$var reg 16 4 partialD [15:0] $end
$var reg 16 5 partialQ [15:0] $end
$var reg 16 6 counterD [15:0] $end
$var reg 16 7 counterQ [15:0] $end
$var reg 16 8 counter2D [15:0] $end
$var reg 16 9 counter2Q [15:0] $end
$var reg 2 : state [1:0] $end
$var reg 2 ; nextState [1:0] $end
$var reg 1 < done $end

$scope module rA $end
$var wire 1 # clk $end
$var wire 1 * we $end
$var wire 6 = a [5:0] $end
$var wire 16 ! di [15:0] $end
$var wire 16 > do [15:0] $end
$var integer 32 ? i $end
$upscope $end


$scope module rB $end
$var wire 1 # clk $end
$var wire 1 . we $end
$var wire 6 @ a [5:0] $end
$var wire 16 " di [15:0] $end
$var wire 16 A do [15:0] $end
$var integer 32 B i $end
$upscope $end


$scope module mult $end
$var wire 1 # clk $end
$var wire 1 $ reset $end
$var wire 16 C A [15:0] $end
$var wire 16 D B [15:0] $end
$var reg 16 E PRODUCT [15:0] $end
$var reg 32 F storeD [31:0] $end
$var reg 32 G storeQ [31:0] $end
$var reg 16 H storeBD [15:0] $end
$var reg 16 I storeBQ [15:0] $end
$var reg 32 J productD [31:0] $end
$var reg 32 K productQ [31:0] $end
$var reg 4 L nextState [3:0] $end
$var reg 4 M state [3:0] $end
$var reg 7 N counterD [6:0] $end
$var reg 7 O counterQ [6:0] $end
$upscope $end

$upscope $end

$upscope $end

$enddefinitions $end

#0
$dumpvars
0#
1<
03
02
1$
0*
0.
bxxxxxxxxxxxxxxxx E
b0000000000000000 !
bxxxxxxxxx +
bxxxxxxxxx ,
bxxxxxxxxx /
bxxxxxxxxx 0
b0000000000000000 "
b0000000000000000 8
bxxxxxxxxxxxxxxxx 9
bxxxxxxxxxxxxxxxx 6
bxxxxxxxxxxxxxxxx 7
bxxxxxxxxxxxxxxxx -
bxxxxxxxxxxxxxxxx 1
bxxxxxxxxxxxxxxxx >
bxxxxxx &
bxxxxxx '
bxxxxxxxxxxxxxxxx C
bxxxxxxxxxxxxxxxx D
bxxxxxxx N
bxxxxxxx O
bxxxx L
bxxxx M
b00 ;
b00000000000000000000000000001010 ?
bxxxxxxxxxxxxxxxx 4
bxxxxxxxxxxxxxxxx 5
bxxxxxxxxxxxxxxxxxxxxxxxxxxxxxxxx J
bxxxxxxxxxxxxxxxxxxxxxxxxxxxxxxxx K
bxxxxxxxxxxxxxxxx A
b00000000000000000000000000001010 B
bxxxxxxxxxxxxxxxx (
bxxxxxxxxxxxxxxxx )
bxx :
bxxxxxxxxxxxxxxxx H
bxxxxxxxxxxxxxxxx I
bxxxxxxxxxxxxxxxxxxxxxxxxxxxxxxxx F
bxxxxxxxxxxxxxxxxxxxxxxxxxxxxxxxx G
bxxxxxx =
bxxxxxx @
b0000 %
$end
#10000
1#
b000000000 ,
b000000 =
b0000000000000000 >
b0000000000000000 -
b0000000000000000 C
b000000000 0
b000000 @
b0000000000000000 A
b0000000000000000 1
b0000000000000000 D
b0000000000000000 9
b0000000000000000 5
b0000000000000000 7
b00 :
b0000000 O
b00000000000000000000000000000000 G
b0000000000000000 I
b00000000000000000000000000000000 K
b0000 M
b000000000 /
b000000000 +
b0000000000000000 4
b0001 L
b0000000 N
b00000000000000000000000000000000 J
b0000000000000000 H
b00000000000000000000000000000000 F
#20000
0#
#30000
1#
#40000
0#
#50000
1#
#60000
0$
b0010 %
0#
b0000000000000000 6
#70000
1#
b0001 M
b0000001 N
#80000
b000000 &
b0001 %
b0000000101000000 !
b0000000110000000 "
0#
1.
1*
b000000001 /
b000000001 +
#90000
1#
b000000001 ,
b000001 =
b000000001 0
b000001 @
b0000001 O
b000000010 /
b000000010 +
b0000010 N
#100000
b0000 %
0#
b000000001 /
b000000001 +
0.
0*
#110000
1#
b0000010 O
b0000011 N
#120000
0#
#130000
1#
b0000011 O
b0000100 N
#140000
0#
#150000
1#
b0000100 O
b0000101 N
#160000
0#
#170000
1#
b0000101 O
b0000110 N
#180000
0#
#190000
1#
b0000110 O
b0000111 N
#200000
b000001 &
b0001 %
b0000001010000000 !
0#
1.
1*
b000000010 /
b000000010 +
#210000
1#
b000000010 ,
b000010 =
b000000010 0
b000010 @
b0000111 O
b000000011 /
b000000011 +
b0001000 N
#220000
b0000 %
0#
b000000010 /
b000000010 +
0.
0*
#230000
1#
b0001000 O
b0001001 N
#240000
0#
#250000
1#
b0001001 O
b0001010 N
#260000
0#
#270000
1#
b0001010 O
b0001011 N
#280000
0#
#290000
1#
b0001011 O
b0001100 N
#300000
0#
#310000
1#
b0001100 O
b0001101 N
#320000
b000010 &
b0001 %
b0000010100000000 "
0#
1.
1*
b000000011 /
b000000011 +
#330000
1#
b000000011 ,
b000011 =
b000000011 0
b000011 @
b0001101 O
b000000100 /
b000000100 +
b0001110 N
#340000
b0000 %
0#
b000000011 /
b000000011 +
0.
0*
#350000
1#
b0001110 O
b0001111 N
#360000
0#
#370000
1#
b0001111 O
b0010000 N
#380000
0#
#390000
1#
b0010000 O
b0010001 N
#400000
0#
#410000
1#
b0010001 O
b0010010 N
#420000
0#
#430000
1#
b0010010 O
b0010011 N
#440000
b000011 &
b0001 %
b0000001000000000 !
b0000001000000000 "
0#
1.
1*
b000000100 /
b000000100 +
#450000
1#
b000000100 ,
b000100 =
b000000100 0
b000100 @
b0010011 O
b000000101 /
b000000101 +
b0010100 N
#460000
b0000 %
0#
b000000100 /
b000000100 +
0.
0*
#470000
1#
b0010100 O
b0010101 N
#480000
0#
#490000
1#
b0010101 O
b0010110 N
#500000
0#
#510000
1#
b0010110 O
b0010111 N
#520000
0#
#530000
1#
b0010111 O
b0011000 N
#540000
0#
#550000
1#
b0011000 O
b0011001 N
#560000
b000100 &
b0001 %
b0000001100000000 !
b0000010100000000 "
0#
1.
1*
b000000101 /
b000000101 +
#570000
1#
b000000101 ,
b000101 =
b000000101 0
b000101 @
b0011001 O
b000000110 /
b000000110 +
b0011010 N
#580000
b0000 %
0#
b000000101 /
b000000101 +
0.
0*
#590000
1#
b0011010 O
b0011011 N
#600000
0#
#610000
1#
b0011011 O
b0011100 N
#620000
0#
#630000
1#
b0011100 O
b0011101 N
#640000
0#
#650000
1#
b0011101 O
b0011110 N
#660000
0#
#670000
1#
b0011110 O
b0011111 N
#680000
b000101 &
b0001 %
b0000001000000000 !
b0000001100000000 "
0#
1.
1*
b000000110 /
b000000110 +
#690000
1#
b000000110 ,
b000110 =
b000000110 0
b000110 @
b0011111 O
b000000111 /
b000000111 +
b0100000 N
#700000
b0000 %
0#
b000000110 /
b000000110 +
0.
0*
#710000
1#
b0100000 O
b0010 L
#720000
0#
#730000
1#
b0010 M
b0000 L
b0000000000000000 E
b0000000000000000 )
#740000
0#
#750000
1#
b0000 M
b0001 L
b0000000 N
#760000
0#
#770000
1#
b0000000 O
b0001 M
b0000001 N
#780000
0#
#790000
1#
b0000001 O
b0000010 N
#800000
b000110 &
b0001 %
b0000000101000000 !
b0000001110000000 "
0#
1.
1*
b000000111 /
b000000111 +
#810000
1#
b000000111 ,
b000111 =
b000000111 0
b000111 @
b0000010 O
b000001000 /
b000001000 +
b0000011 N
#820000
b0000 %
0#
b000000111 /
b000000111 +
0.
0*
#830000
1#
b0000011 O
b0000100 N
#840000
0#
#850000
1#
b0000100 O
b0000101 N
#860000
0#
#870000
1#
b0000101 O
b0000110 N
#880000
0#
#890000
1#
b0000110 O
b0000111 N
#900000
0#
#910000
1#
b0000111 O
b0001000 N
#920000
b000111 &
b0001 %
b0000001110000000 !
b0000010100000000 "
0#
1.
1*
b000001000 /
b000001000 +
#930000
1#
b000001000 ,
b001000 =
b000001000 0
b001000 @
b0001000 O
b000001001 /
b000001001 +
b0001001 N
#940000
b0000 %
0#
b000001000 /
b000001000 +
0.
0*
#950000
1#
b0001001 O
b0001010 N
#960000
0#
#970000
1#
b0001010 O
b0001011 N
#980000
0#
#990000
1#
b0001011 O
b0001100 N
#1000000
0#
#1010000
1#
b0001100 O
b0001101 N
#1020000
0#
#1030000
1#
b0001101 O
b0001110 N
#1040000
b001000 &
b0001 %
b0000010010000000 !
b0000010000000000 "
0#
1.
1*
b000001001 /
b000001001 +
#1050000
1#
b000001001 ,
b001001 =
b000001001 0
b001001 @
b0001110 O
b000000000 /
b000000000 +
b01 ;
b0001111 N
#1060000
b0000 %
0#
b000001001 /
b000001001 +
b00 ;
0.
0*
#1070000
1#
b0001111 O
b0010000 N
#1080000
0#
#1090000
1#
b0010000 O
b0010001 N
#1100000
0#
#1110000
1#
b0010001 O
b0010010 N
#1120000
0#
#1130000
1#
b0010010 O
b0010011 N
#1140000
0#
#1150000
1#
b0010011 O
b0010100 N
#1160000
b001001 &
b0001 %
b0000001000000000 !
b0000001100000000 "
0#
1.
1*
b000000000 /
b000000000 +
b01 ;
#1170000
1#
b000000000 ,
b000000 =
b0000000101000000 >
b0000000101000000 -
b0000000101000000 C
b000000000 0
b000000 @
b0000000110000000 A
b0000000110000000 1
b0000000110000000 D
b01 :
b0010100 O
0.
0*
b0000000000000001 8
b0010101 N
#1180000
b0000 %
0#
#1190000
1#
b0000000000000001 9
b0010101 O
b0000000000000010 8
b0010110 N
#1200000
0#
#1210000
1#
b0000000000000010 9
b0010110 O
b0000000000000011 8
b0010111 N
#1220000
0#
#1230000
1#
b0000000000000011 9
b0010111 O
b0000000000000100 8
b0011000 N
#1240000
0#
#1250000
1#
b0000000000000100 9
b0011000 O
b0000000000000101 8
b0011001 N
#1260000
0#
#1270000
1#
b0000000000000101 9
b0011001 O
b0000000000000110 8
b0011010 N
#1280000
b001010 &
